{
"type": "FeatureCollection",
"name": "geojson_hail_point_20230803T09",
"crs": { "type": "name", "properties": { "name": "urn:ogc:def:crs:OGC:1.3:CRS84" } },
"features": [
{ "type": "Feature", "properties": { "case": "hail", "timestamp": "20230803T09" }, "geometry": { "type": "Point", "coordinates": [ -79.17, 44.65 ] } }
]
}
